odoo/addons/hr_employee_language/README.rst
odoo/addons/hr_employee_language/__init__.py
odoo/addons/hr_employee_language/__manifest__.py
odoo/addons/hr_employee_language/i18n/hr_employee_language.pot
odoo/addons/hr_employee_language/i18n/it.po
odoo/addons/hr_employee_language/models/__init__.py
odoo/addons/hr_employee_language/models/hr_employee.py
odoo/addons/hr_employee_language/models/hr_employee_language.py
odoo/addons/hr_employee_language/readme/CONTRIBUTORS.rst
odoo/addons/hr_employee_language/readme/DESCRIPTION.rst
odoo/addons/hr_employee_language/readme/USAGE.rst
odoo/addons/hr_employee_language/security/ir.model.access.csv
odoo/addons/hr_employee_language/static/description/icon.png
odoo/addons/hr_employee_language/static/description/index.html
odoo/addons/hr_employee_language/views/hr_employee.xml
odoo/addons/hr_employee_language/views/hr_employee_language.xml
odoo12_addon_hr_employee_language-12.0.1.0.0.99.dev6.dist-info/METADATA
odoo12_addon_hr_employee_language-12.0.1.0.0.99.dev6.dist-info/WHEEL
odoo12_addon_hr_employee_language-12.0.1.0.0.99.dev6.dist-info/top_level.txt
odoo12_addon_hr_employee_language-12.0.1.0.0.99.dev6.dist-info/RECORD
